wda/__init__.py
wda/_proto.py
wda/exceptions.py
wda/requests_usbmux.py
wda/usbmux.py
wda/utils.py
wda/xcui_element_types.py
cc12703_facebook_wda-2.0.2.dist-info/AUTHORS
cc12703_facebook_wda-2.0.2.dist-info/LICENSE
cc12703_facebook_wda-2.0.2.dist-info/METADATA
cc12703_facebook_wda-2.0.2.dist-info/WHEEL
cc12703_facebook_wda-2.0.2.dist-info/pbr.json
cc12703_facebook_wda-2.0.2.dist-info/top_level.txt
cc12703_facebook_wda-2.0.2.dist-info/RECORD
